playscript/__init__.py
playscript/psc.py
playscript/conv/__init__.py
playscript/conv/fountain.py
playscript/conv/html.py
playscript/conv/json.py
playscript/conv/pdf.py
playscript/conv/templates/html/default.html
playscript/conv/templates/html/scripts/app.js
playscript/conv/templates/html/scripts/init.js
playscript/conv/templates/html/scripts/psc.js
playscript/conv/templates/html/styles/app.css
playscript/conv/templates/html/styles/psc.css
playscript-0.2.8.dist-info/LICENSE
playscript-0.2.8.dist-info/METADATA
playscript-0.2.8.dist-info/WHEEL
playscript-0.2.8.dist-info/top_level.txt
playscript-0.2.8.dist-info/RECORD
