Metadata-Version: 2.1
Name: playscript
Version: 0.2.8
Summary: playscript - Structure for Play Scripts
Home-page: https://github.com/satamame/playscript
Author: satamame
Author-email: satamame@gmail.com
License: MIT
Keywords: theater,play,script,dialogue
Classifier: Development Status :: 3 - Alpha
Classifier: License :: OSI Approved :: MIT License
Classifier: Programming Language :: Python :: 3.8
Classifier: Programming Language :: Python :: 3.9
Classifier: Programming Language :: Python :: 3.10
Classifier: Programming Language :: Python :: 3.11
Classifier: Programming Language :: Python :: 3.12
Requires-Python: ~=3.8
License-File: LICENSE
Requires-Dist: jinja2>=2.11.3
Requires-Dist: reportlab>=3.6.1
